[
  {
    "title": "Nonresponse Bias Analysis of Body Mass Index in the Eating and Health Module",
    "url": "https://explore.openaire.eu/search/publication?articleId=od_______645::1376de6422685b4fa4ab7b04826b68d5",
    "search_term": "Eating and Health Module",
    "dataset": "dataset-051"
  },
  {
    "title": "Nonresponse Bias Analysis of Body Mass Index Data in the Eating and Health Module",
    "url": "https://explore.openaire.eu/search/publication?articleId=od_______645::df6e807e38486c92e95a4eb55ffdd5c2",
    "search_term": "Eating and Health Module",
    "dataset": "dataset-051"
  },
  {
    "title": "Federal nutrition programs and childhood obesity: Inside the black box",
    "url": "https://explore.openaire.eu/search/publication?articleId=dedup_wf_001::a5e5b53a81a92ba352d8995c75ec2e3f",
    "search_term": "Eating and Health Module",
    "dataset": "dataset-051"
  },
  {
    "title": "Grazing, Goods and Girth: Determinants and Effects",
    "url": "https://explore.openaire.eu/search/publication?articleId=dedup_wf_001::6ee3dd0600b8e3070415ec9896c5b3f1",
    "search_term": "Eating and Health Module",
    "dataset": "dataset-051"
  },
  {
    "title": "The travel\u2013obesity connection: discerning the impacts of commuting trips with the perspective of individual energy expenditure and time use",
    "url": "https://explore.openaire.eu/search/publication?articleId=od_______645::32b8a246f6efcedda3c0d884351deae3",
    "search_term": "Eating and Health Module",
    "dataset": "dataset-051"
  },
  {
    "title": "Mother/Child Eating and Drinking Patterns by Weight and Ethnicity",
    "url": "https://explore.openaire.eu/search/publication?articleId=od_______645::c616828191b2302c932d351d5e85cdde",
    "search_term": "Eating and Health Module",
    "dataset": "dataset-051"
  }
]